tempdrive/__init__.py
tempdrive/_byref.py
tempdrive/_drive_letter.py
tempdrive/_exceptions.py
tempdrive/_free_drive.py
tempdrive/_subst.py
tempdrive/_tempdrive.py
tempdrive/_winapi.py
tempdrive/py.typed
tempdrive-1.0.dist-info/METADATA
tempdrive-1.0.dist-info/WHEEL
tempdrive-1.0.dist-info/licenses/LICENSE
tempdrive-1.0.dist-info/RECORD
