Metadata-Version: 2.4
Name: tempdrive
Version: 1.0
Summary: TODO
Project-URL: Homepage, https://github.com/petamas/python-tempdrive
Project-URL: Bug Tracker, https://github.com/petamas/python-tempdrive/issues
Author-email: Tamás PEREGI <petamas@gmail.com>
License-Expression: MIT
License-File: LICENSE
Classifier: License :: OSI Approved :: MIT License
Classifier: Operating System :: Microsoft :: Windows
Classifier: Programming Language :: Python :: 3.10
Classifier: Programming Language :: Python :: 3.11
Classifier: Programming Language :: Python :: 3.12
Classifier: Programming Language :: Python :: 3.13
Requires-Python: >=3.10
Requires-Dist: ntstatus<3,>=2.0
